thonnycontrib/__init__.py
thonnycontrib/environement_vars.py
thonnycontrib/exception_response.py
thonnycontrib/exceptions.py
thonnycontrib/plugin_loader.py
thonnycontrib/properties.py
thonnycontrib/utils.py
thonnycontrib/backend/__init__.py
thonnycontrib/backend/ast_parser.py
thonnycontrib/backend/doctest_parser.py
thonnycontrib/backend/evaluator.py
thonnycontrib/backend/l1test_backend.py
thonnycontrib/backend/models.py
thonnycontrib/backend/verdicts/ExampleVerdict.py
thonnycontrib/backend/verdicts/ExceptionVerdict.py
thonnycontrib/backend/verdicts/FailedVerdict.py
thonnycontrib/backend/verdicts/FailedWhenExceptionExpectedVerdict.py
thonnycontrib/backend/verdicts/PassedSetupVerdict.py
thonnycontrib/backend/verdicts/PassedVerdict.py
thonnycontrib/backend/verdicts/__init__.py
thonnycontrib/frontend/__init__.py
thonnycontrib/frontend/l1test_runner.py
thonnycontrib/frontend/cli/__init__.py
thonnycontrib/frontend/cli/command_line.py
thonnycontrib/frontend/cli/l1test_cli_runner.py
thonnycontrib/frontend/gui/ThonnyLogsGenerator.py
thonnycontrib/frontend/gui/__init__.py
thonnycontrib/frontend/gui/l1test_gui_runner.py
thonnycontrib/frontend/gui/docstring_generator/__init__.py
thonnycontrib/frontend/gui/docstring_generator/doc_generator.py
thonnycontrib/frontend/gui/docstring_generator/doc_template.py
thonnycontrib/frontend/gui/main_generator/__init__.py
thonnycontrib/frontend/gui/main_generator/main_generator.py
thonnycontrib/frontend/gui/outlines_menu/__init__.py
thonnycontrib/frontend/gui/outlines_menu/l1test_outliner_menu.py
thonnycontrib/frontend/gui/views/__init__.py
thonnycontrib/frontend/gui/views/l1test_error_view.py
thonnycontrib/frontend/gui/views/l1test_reporter.py
thonnycontrib/frontend/gui/views/l1test_treeview.py
thonnycontrib/i18n/__init__.py
thonnycontrib/i18n/languages.py
thonnycontrib/i18n/locale/l1test.pot
thonnycontrib/i18n/locale/en_US/LC_MESSAGES/l1test.mo
thonnycontrib/i18n/locale/en_US/LC_MESSAGES/l1test.po
xpycli-1.0.dist-info/LICENSE
xpycli-1.0.dist-info/METADATA
xpycli-1.0.dist-info/WHEEL
xpycli-1.0.dist-info/top_level.txt
xpycli-1.0.dist-info/RECORD
